natia/__init__.py
natia/kb/__init__.py
natia/kb/client.py
natia/kb/docdb/__init__.py
natia/kb/docdb/base.py
natia/kb/docdb/mongodb.py
natia/kb/document/__init__.py
natia/kb/document/document.py
natia/kb/document/id.py
natia/kb/vecdb/__init__.py
natia/kb/vecdb/base.py
natia/kb/vecdb/doc2vec/__init__.py
natia/kb/vecdb/doc2vec/base.py
natia/kb/vecdb/doc2vec/doc2text.py
natia/kb/vecdb/doc2vec/sentence_transformer.py
natia/kb/vecdb/qdrant/__init__.py
natia/kb/vecdb/qdrant/client.py
tests/__init__.py
tests/test_docdb.py
tests/test_kb.py
natia-0.0.3.dist-info/METADATA
natia-0.0.3.dist-info/WHEEL
natia-0.0.3.dist-info/top_level.txt
natia-0.0.3.dist-info/RECORD
