Metadata-Version: 2.1
Name: natia
Version: 0.0.3
Summary: Natia stands for NATural IterAction. We aim to build a toolkit that leverages LLMs.
Author-email: Isaac Fei <isaac.omega.fei@gmail.com>
Project-URL: Homepage, https://github.com/Isaac-Fate/natural-interact
Requires-Python: >=3.11
